py3_test/__init__.py
py3_test/__main__.py
py3_test/cli.py
py3_test/algorithm/1.jpg
py3_test/algorithm/1_new.jpg
py3_test/algorithm/2.jpg
py3_test/algorithm/2.py
py3_test/algorithm/2_new.jpg
py3_test/algorithm/3.jpg
py3_test/algorithm/3.py
py3_test/algorithm/3_new.jpg
py3_test/algorithm/4.jpg
py3_test/algorithm/4_new.jpg
py3_test/algorithm/5.jpg
py3_test/algorithm/5_new.jpg
py3_test/algorithm/6.jpg
py3_test/algorithm/6_new.jpg
py3_test/algorithm/__init__.py
py3_test/algorithm/modified.jpg
py3_test/algorithm/result.jpg
py3_test/algorithm/result2.jpg
py3_test/algorithm/test.py
py3_test/algorithm/wilson_score.py
py3_test/algorithm/保险资讯处理流程说明.docx
py3_test/algorithm/leetcood/__init__.py
py3_test/algorithm/leetcood/array/1.py
py3_test/algorithm/leetcood/array/2.py
py3_test/algorithm/leetcood/array/3.py
py3_test/algorithm/leetcood/array/4.py
py3_test/algorithm/leetcood/array/5.py
py3_test/algorithm/leetcood/array/6.py
py3_test/algorithm/leetcood/array/__init__.py
py3_test/analysis/ipython-notebook/__init__.py
py3_test/analysis/ipython-notebook/test.ipynb
py3_test/analysis/ipython-notebook/.ipynb_checkpoints/test-checkpoint.ipynb
py3_test/bigdata/__init__.py
py3_test/bigdata/gaodeApi/gaodeApi.py
py3_test/bigdata/gaodeApi/kn1_zx_need_city.ctsh
py3_test/bigdata/gaodeApi/kn1_zx_need_city.sh
py3_test/bigdata/hdfs/__init__.py
py3_test/bigdata/hdfs/hdfs_client.py
py3_test/bigdata/hive_test/1.py
py3_test/bigdata/hive_test/__init__.py
py3_test/bigdata/hive_test/presto_client.py
py3_test/bigdata/hive_test/pyhive_client.py
py3_test/bigdata/kafka_test/KafkaConsumer.py
py3_test/bigdata/kafka_test/KafkaConsumerQueue.py
py3_test/bigdata/kafka_test/__init__.py
py3_test/bigdata/kafka_test/kafkaTest.py
py3_test/bigdata/kafka_test/pykafka_client.py
py3_test/bigdata/postgresql/__init__.py
py3_test/bigdata/postgresql/detail_10minute.py
py3_test/bigdata/postgresql/detail_10minute_tmp.py
py3_test/bigdata/postgresql/pg_client.py
py3_test/bigdata/postgresql/pgbak.py
py3_test-0.3.0.dist-info/METADATA
py3_test-0.3.0.dist-info/WHEEL
py3_test-0.3.0.dist-info/entry_points.txt
py3_test-0.3.0.dist-info/RECORD
