Metadata-Version: 2.1
Name: py3_test
Version: 0.3.0
Summary: Add a short description here
Project-URL: Homepage, https://github.com/tiangolo/fastapi
Project-URL: Documentation, https://fastapi.tiangolo.com/
Project-URL: Repository, https://github.com/tiangolo/fastapi
Author-email: lijc210 <lijc210@gmail.com>
License: MIT
Requires-Python: >=3.9
Requires-Dist: apscheduler~=3.10.1
Requires-Dist: celery~=5.2.7
Requires-Dist: clickhouse-driver~=0.2.6
Requires-Dist: click~=8.1.6
Requires-Dist: cython~=0.29.34
Requires-Dist: dbutils~=3.0.3
Requires-Dist: easybase~=1.1.3
Requires-Dist: elasticsearch~=8.7.0
Requires-Dist: ezdxf~=1.0.3
Requires-Dist: fabric~=3.0.1
Requires-Dist: fastapi~=0.95.1
Requires-Dist: feedparser~=6.0.10
Requires-Dist: flask~=2.2.3
Requires-Dist: func-timeout~=4.3.5
Requires-Dist: gensim~=4.3.1
Requires-Dist: gevent~=22.10.2
Requires-Dist: gitpython~=3.1.31
Requires-Dist: graphene~=3.2.2
Requires-Dist: grequests~=0.6.0
Requires-Dist: happybase~=1.2.0
Requires-Dist: hdfs~=2.7.0
Requires-Dist: huaweicloudsdkcore==3.1.19
Requires-Dist: itchat~=1.3.10
Requires-Dist: jieba~=0.42.1
Requires-Dist: kafka~=1.3.5
Requires-Dist: ldap3~=2.9.1
Requires-Dist: line-profiler~=4.0.3
Requires-Dist: locust~=2.15.1
Requires-Dist: lxml~=4.9.2
Requires-Dist: marisa-trie~=0.8.0
Requires-Dist: matplotlib~=3.7.1
Requires-Dist: memory-profiler~=0.61.0
Requires-Dist: numba~=0.57.0
Requires-Dist: odps~=3.5.1
Requires-Dist: opencv-python~=4.7.0.72
Requires-Dist: openpyxl~=3.1.2
Requires-Dist: pandas~=2.0.1
Requires-Dist: pickledb~=0.9.2
Requires-Dist: pillow~=9.5.0
Requires-Dist: pinyin~=0.4.0
Requires-Dist: playwright~=1.33.0
Requires-Dist: psycopg2-binary~=2.9.6
Requires-Dist: py2neo~=2021.2.3
Requires-Dist: pyautogui~=0.9.53
Requires-Dist: pycrypto~=2.6.1
Requires-Dist: pyecharts~=2.0.3
Requires-Dist: pyftpdlib~=1.5.7
Requires-Dist: pyhive~=0.6.5
Requires-Dist: pykafka~=2.8.0
Requires-Dist: pymongo~=4.3.3
Requires-Dist: pymysql~=1.0.3
Requires-Dist: pypandoc-binary~=1.11
Requires-Dist: pypdf2~=3.0.1
Requires-Dist: pyqt5~=5.15.9
Requires-Dist: pyquery~=2.0.0
Requires-Dist: pyspark~=3.4.0
Requires-Dist: python-ldap~=3.4.3
Requires-Dist: python-pptx~=0.6.21
Requires-Dist: pytrie~=0.4.0
Requires-Dist: qiniu~=7.10.0
Requires-Dist: redis-py-cluster==2.1.3
Requires-Dist: redis==3.5.3
Requires-Dist: requests-html~=0.10.0
Requires-Dist: requests~=2.28.2
Requires-Dist: retry~=0.9.2
Requires-Dist: sanic-auth~=0.3.0
Requires-Dist: sanic-openapi~=21.12.0
Requires-Dist: sanic~=23.3.0
Requires-Dist: schedule~=1.2.0
Requires-Dist: scikit-learn~=1.2.2
Requires-Dist: scipy~=1.10.1
Requires-Dist: selenium~=4.9.0
Requires-Dist: simhash~=2.1.2
Requires-Dist: snapshot-phantomjs~=0.0.3
Requires-Dist: sqlalchemy~=2.0.12
Requires-Dist: tornado~=6.3.1
Requires-Dist: tqdm~=4.65.0
Requires-Dist: tuling~=1.2
Requires-Dist: tushare~=1.2.89
Requires-Dist: wget~=3.2
Requires-Dist: wheel~=0.40.0
